<?xml version="1.0" encoding="UTF-8"?>
<prefab>
  <property name="Zoning" value="ResidentialOld" />
  <property name="AllowedTownships" value="city,town,rural,wilderness" />
  <property name="RotationToFaceNorth" value="2" />
  <property name="CopyAirBlocks" value="True" />
  <property name="ExcludeDistantPOIMesh" value="False" />
  <property name="DistantPOIYOffset" value="0" />
  <property name="AllowTopSoilDecorations" value="False" />
  <property name="TraderArea" value="False" />
  <property name="SleeperVolumeSize" value="9, 5, 8#10, 4, 9#8, 8, 11#9, 4, 9" />
  <property name="SleeperVolumeStart" value="8, 3, 23#8, 8, 22#12, 13, 17#14, 3, 14" />
  <property name="SleeperVolumeGameStageAdjust" value=",,," />
  <property name="SleeperIsLootVolume" value="False,False,False,True" />
  <property name="EditorGroups" value="house old" />
  <property name="YOffset" value="-1" />
  <property name="SleeperIsBossVolume" value="False,False,False,False" />
  <property name="QuestTags" value="clear,fetch,hidden_cache" />
  <property name="DifficultyTier" value="1" />
  <property name="SleeperVolumeGroup" value="S_-Group_Generic_Zombie,1,1,S_-Group_Generic_Zombie,2,2,S_-_Group_Ghost_Town,1,1,S_-Group_Generic_Zombie,2,2" />
  <property name="ExcludePOICulling" value="False" />
  <property name="SleeperVolumeGroupId" value="0,0,0,0" />
  <property name="SleeperVolumeFlags" value="0,0,0,0" />
  <property class="Stats">
    <property name="TotalVertices" value="222882" />
    <property name="TotalTriangles" value="197958" />
    <property class="BlockEntities">
      <property name="Vertices" value="151220" />
      <property name="Triangles" value="153040" />
    </property>
    <property class="ChunkMeshes0">
      <property name="Vertices" value="58090" />
      <property name="Triangles" value="31206" />
    </property>
    <property class="ChunkMeshes1">
      <property name="Vertices" value="0" />
      <property name="Triangles" value="0" />
    </property>
    <property class="ChunkMeshes2">
      <property name="Vertices" value="608" />
      <property name="Triangles" value="344" />
    </property>
    <property class="ChunkMeshes3">
      <property name="Vertices" value="0" />
      <property name="Triangles" value="0" />
    </property>
    <property class="ChunkMeshes4">
      <property name="Vertices" value="8442" />
      <property name="Triangles" value="6336" />
    </property>
    <property class="ChunkMeshes5">
      <property name="Vertices" value="0" />
      <property name="Triangles" value="0" />
    </property>
    <property class="ChunkMeshes6">
      <property name="Vertices" value="0" />
      <property name="Triangles" value="0" />
    </property>
    <property class="ChunkMeshes7">
      <property name="Vertices" value="4506" />
      <property name="Triangles" value="7024" />
    </property>
    <property class="ChunkMeshes8">
      <property name="Vertices" value="0" />
      <property name="Triangles" value="0" />
    </property>
    <property class="ChunkMeshes9">
      <property name="Vertices" value="16" />
      <property name="Triangles" value="8" />
    </property>
  </property>
  <property class="IndexedBlockOffsets">
    <property class="FetchContainer">
      <property name="0" value="20, 11, 29" />
      <property name="1" value="21, 6, 28" />
    </property>
    <property class="Rally">
      <property name="0" value="24, 2, 30" />
    </property>
  </property>
</prefab>